LICENSE
MANIFEST.in
README.md
pyproject.toml
setup.cfg
setup.py
test.py
ulexecve.py
ulexecve.egg-info/PKG-INFO
ulexecve.egg-info/SOURCES.txt
ulexecve.egg-info/dependency_links.txt
ulexecve.egg-info/entry_points.txt
ulexecve.egg-info/requires.txt
ulexecve.egg-info/top_level.txt