Metadata-Version: 2.1
Name: ulexecve
Version: 1.3
Summary: Userland execve utility
Home-page: https://github.com/anvilsecure/ulexecve
Author: Anvil Secure Inc.
Author-email: gvb@anvilsecure.com
License: UNKNOWN
Keywords: userland execve
Platform: UNKNOWN
Classifier: Programming Language :: Python :: 2
Classifier: Programming Language :: Python :: 3
Classifier: License :: OSI Approved :: MIT License
Classifier: Operating System :: POSIX
Classifier: Development Status :: 5 - Production/Stable
Classifier: Development Status :: 5 - Production/Stable
Classifier: Environment :: Console
Classifier: Intended Audience :: Developers
Classifier: Intended Audience :: Information Technology
Classifier: Intended Audience :: System Administrators
Requires-Python: >=2.7
Provides-Extra: test
